dbgpy/__init__.py
dbgpy/_config.py
dbgpy/_dbg.py
dbgpy/_stack_inspect.py
dbgpy-0.2.1.dist-info/METADATA
dbgpy-0.2.1.dist-info/WHEEL
dbgpy-0.2.1.dist-info/top_level.txt
dbgpy-0.2.1.dist-info/RECORD
